Workbook

Sheet ⚙ Setup
A1: 💰 ULTIMATE ANNUAL BUDGET
A2: Dark Mode Edition · Google Sheets / Excel Compatible
A5: Personal Information
A6: Your Name | B6: camill rogers | C6: ← Enter your information here
A7: Monthly Net Income | B7: 5000
A8: Savings Goal % | B8: 0.2
A9: Currency | B9: USD
A10: Year | B10: 2026
A11: Pay Frequency | B11: Biweekly
A14: Expense Categories (customize)
A15: Housing
A16: Transportation
A17: Food & Groceries | B17: ← Optional budget limit
A18: Utilities | B18: ← Optional budget limit
A19: Insurance | B19: ← Optional budget limit
A20: Healthcare | B20: ← Optional budget limit
A21: Entertainment | B21: ← Optional budget limit
A22: Clothing | B22: ← Optional budget limit
A23: Personal Care | B23: ← Optional budget limit
A24: Education | B24: ← Optional budget limit
A25: Subscriptions | B25: ← Optional budget limit
A26: Pets | B26: ← Optional budget limit
A27: Gifts & Donations | B27: ← Optional budget limit
A28: Travel | B28: ← Optional budget limit
A29: Miscellaneous | B29: ← Optional budget limit

Sheet 📊 Annual Dashboard
A1: 📊 ANNUAL DASHBOARD 2025
O2: Category | P2: Annual Total
B3: TOTAL INCOME | D3: TOTAL EXPENSES | F3: NET SAVINGS | H3: SAVINGS RATE | J3: DEBT PAYMENTS | L3: NET WORTH | O3: Housing | P3: =SUM(Jan:Dec!C17) -> 18000
B4: =B20 -> 62970 | D4: =C20 -> 45595 | F4: =D20 -> 17375 | H4: =IFERROR(D20/B20,0) -> 0.27592504 | J4: ='💳 Debt Tracker'!D10 -> 502 | L4: ='📈 Net Worth'!D4 -> 114000 | O4: Transportation | P4: =SUM(Jan:Dec!C18) -> 4250
O5: Food & Groceries | P5: =SUM(Jan:Dec!C19) -> 7780
A6: Monthly Summary | O6: Utilities | P6: =SUM(Jan:Dec!C20) -> 2000
A7: Month | B7: Income | C7: Expenses | D7: Net | E7: Savings % | F7: Status | O7: Insurance | P7: =SUM(Jan:Dec!C21) -> 3000
A8: Jan | B8: =IFERROR(Jan!C4,0) -> 5050 | C8: =IFERROR(Jan!C5,0) -> 3395 | D8: =B8-C8 -> 1655 | E8: =IFERROR(D8/B8,0) -> 0.32772277 | F8: =IF(D8>=0,"✓ Positive","✗ Deficit") -> ✓ Positive | O8: Healthcare | P8: =SUM(Jan:Dec!C22) -> 730
A9: Feb | B9: =IFERROR(Feb!C4,0) -> 5050 | C9: =IFERROR(Feb!C5,0) -> 3330 | D9: =B9-C9 -> 1720 | E9: =IFERROR(D9/B9,0) -> 0.34059406 | F9: =IF(D9>=0,"✓ Positive","✗ Deficit") -> ✓ Positive | O9: Entertainment | P9: =SUM(Jan:Dec!C23) -> 1800
A10: Mar | B10: =IFERROR(Mar!C4,0) -> 5050 | C10: =IFERROR(Mar!C5,0) -> 3560 | D10: =B10-C10 -> 1490 | E10: =IFERROR(D10/B10,0) -> 0.2950495 | F10: =IF(D10>=0,"✓ Positive","✗ Deficit") -> ✓ Positive | O10: Clothing | P10: =SUM(Jan:Dec!C24) -> 1830
A11: Apr | B11: =IFERROR(Apr!C4,0) -> 5580 | C11: =IFERROR(Apr!C5,0) -> 3685 | D11: =B11-C11 -> 1895 | E11: =IFERROR(D11/B11,0) -> 0.33960573 | F11: =IF(D11>=0,"✓ Positive","✗ Deficit") -> ✓ Positive | O11: Personal Care | P11: =SUM(Jan:Dec!C25) -> 785
A12: May | B12: =IFERROR(May!C4,0) -> 5580 | C12: =IFERROR(May!C5,0) -> 3790 | D12: =B12-C12 -> 1790 | E12: =IFERROR(D12/B12,0) -> 0.32078853 | F12: =IF(D12>=0,"✓ Positive","✗ Deficit") -> ✓ Positive | O12: Education | P12: =SUM(Jan:Dec!C26) -> 300
A13: Jun | B13: =IFERROR(Jun!C4,0) -> 5080 | C13: =IFERROR(Jun!C5,0) -> 4375 | D13: =B13-C13 -> 705 | E13: =IFERROR(D13/B13,0) -> 0.13877953 | F13: =IF(D13>=0,"✓ Positive","✗ Deficit") -> ✓ Positive | O13: Subscriptions | P13: =SUM(Jan:Dec!C27) -> 900
A14: Jul | B14: =IFERROR(Jul!C4,0) -> 5880 | C14: =IFERROR(Jul!C5,0) -> 3430 | D14: =B14-C14 -> 2450 | E14: =IFERROR(D14/B14,0) -> 0.41666667 | F14: =IF(D14>=0,"✓ Positive","✗ Deficit") -> ✓ Positive | O14: Pets | P14: =SUM(Jan:Dec!C28) -> 0
A15: Aug | B15: =IFERROR(Aug!C4,0) -> 5080 | C15: =IFERROR(Aug!C5,0) -> 3980 | D15: =B15-C15 -> 1100 | E15: =IFERROR(D15/B15,0) -> 0.21653543 | F15: =IF(D15>=0,"✓ Positive","✗ Deficit") -> ✓ Positive | O15: Gifts & Donations | P15: =SUM(Jan:Dec!C29) -> 1320
A16: Sep | B16: =IFERROR(Sep!C4,0) -> 5080 | C16: =IFERROR(Sep!C5,0) -> 3520 | D16: =B16-C16 -> 1560 | E16: =IFERROR(D16/B16,0) -> 0.30708661 | F16: =IF(D16>=0,"✓ Positive","✗ Deficit") -> ✓ Positive | O16: Travel | P16: =SUM(Jan:Dec!C30) -> 1750
A17: Oct | B17: =IFERROR(Oct!C4,0) -> 5380 | C17: =IFERROR(Oct!C5,0) -> 3560 | D17: =B17-C17 -> 1820 | E17: =IFERROR(D17/B17,0) -> 0.33828996 | F17: =IF(D17>=0,"✓ Positive","✗ Deficit") -> ✓ Positive | O17: Miscellaneous | P17: =SUM(Jan:Dec!C31) -> 1150
A18: Nov | B18: =IFERROR(Nov!C4,0) -> 5080 | C18: =IFERROR(Nov!C5,0) -> 4135 | D18: =B18-C18 -> 945 | E18: =IFERROR(D18/B18,0) -> 0.18602362 | F18: =IF(D18>=0,"✓ Positive","✗ Deficit") -> ✓ Positive
A19: Dec | B19: =IFERROR(Dec!C4,0) -> 5080 | C19: =IFERROR(Dec!C5,0) -> 4835 | D19: =B19-C19 -> 245 | E19: =IFERROR(D19/B19,0) -> 0.048228346 | F19: =IF(D19>=0,"✓ Positive","✗ Deficit") -> ✓ Positive
A20: TOTAL | B20: =SUM(B8:B19) -> 62970 | C20: =SUM(C8:C19) -> 45595 | D20: =SUM(D8:D19) -> 17375 | E20: =IFERROR(D20/B20,0) -> 0.27592504

Sheet Jan
A1: ="📅 JAN "&'⚙ Setup'!$B$10&" · Monthly Budget" -> 📅 JAN 2026 · Monthly Budget
A2: INCOME | C2: EXPENSES | E2: NET
A3: =C4 -> 5050 | C3: =C5 -> 3395 | E3: =C4-C5 -> 1655
B4: Total Income | C4: =IFERROR(C13,0) -> 5050
B5: Total Expenses | C5: =IFERROR(C32,0) -> 3395
A6: Income
A7: Source | B7: Notes | C7: Amount | D7: Budget | E7: Difference
A8: Primary Salary | C8: =IFERROR('⚙ Setup'!$B$7,0) -> 5000 | D8: =IFERROR(IF(ISNUMBER('⚙ Setup'!$B$7),'⚙ Setup'!$B$7,0),0) -> 5000 | E8: =C8-D8 -> 0
A9: Secondary Income | C9: 0 | D9: 0 | E9: =C9-D9 -> 0
A10: Freelance / Side Hustle | C10: 0 | D10: 200 | E10: =C10-D10 -> -200
A11: Investment Income | C11: 50 | D11: 50 | E11: =C11-D11 -> 0
A12: Other Income | C12: 0 | D12: 0 | E12: =C12-D12 -> 0
A13: TOTAL INCOME | C13: =SUM(C8:C12) -> 5050 | D13: =SUM(D8:D12) -> 5250
A15: Expenses
A16: Category | B16: Notes | C16: Actual | D16: Budget | E16: Difference
A17: Housing | C17: 1500 | D17: {=IFERROR(IF(ISNUMBER(INDEX('⚙ Setup'!$B:$B,ROW()-2)),INDEX('⚙ Setup'!$B:$B,ROW()-2),0),0)} -> 0 | E17: =D17-C17 -> -1500
A18: Transportation | C18: 350 | D18: {=IFERROR(IF(ISNUMBER(INDEX('⚙ Setup'!$B:$B,ROW()-2)),INDEX('⚙ Setup'!$B:$B,ROW()-2),0),0)} -> 0 | E18: =D18-C18 -> -350
A19: Food & Groceries | C19: 580 | D19: {=IFERROR(IF(ISNUMBER(INDEX('⚙ Setup'!$B:$B,ROW()-2)),INDEX('⚙ Setup'!$B:$B,ROW()-2),0),0)} -> 0 | E19: =D19-C19 -> -580
A20: Utilities | C20: 180 | D20: {=IFERROR(IF(ISNUMBER(INDEX('⚙ Setup'!$B:$B,ROW()-2)),INDEX('⚙ Setup'!$B:$B,ROW()-2),0),0)} -> 0 | E20: =D20-C20 -> -180
A21: Insurance | C21: 250 | D21: {=IFERROR(IF(ISNUMBER(INDEX('⚙ Setup'!$B:$B,ROW()-2)),INDEX('⚙ Setup'!$B:$B,ROW()-2),0),0)} -> 0 | E21: =D21-C21 -> -250
A22: Healthcare | C22: 100 | D22: {=IFERROR(IF(ISNUMBER(INDEX('⚙ Setup'!$B:$B,ROW()-2)),INDEX('⚙ Setup'!$B:$B,ROW()-2),0),0)} -> 0 | E22: =D22-C22 -> -100
A23: Entertainment | C23: 120 | D23: {=IFERROR(IF(ISNUMBER(INDEX('⚙ Setup'!$B:$B,ROW()-2)),INDEX('⚙ Setup'!$B:$B,ROW()-2),0),0)} -> 0 | E23: =D23-C23 -> -120
A24: Clothing | C24: 50 | D24: {=IFERROR(IF(ISNUMBER(INDEX('⚙ Setup'!$B:$B,ROW()-2)),INDEX('⚙ Setup'!$B:$B,ROW()-2),0),0)} -> 0 | E24: =D24-C24 -> -50
A25: Personal Care | C25: 60 | D25: {=IFERROR(IF(ISNUMBER(INDEX('⚙ Setup'!$B:$B,ROW()-2)),INDEX('⚙ Setup'!$B:$B,ROW()-2),0),0)} -> 0 | E25: =D25-C25 -> -60
A26: Education | C26: 0 | D26: {=IFERROR(IF(ISNUMBER(INDEX('⚙ Setup'!$B:$B,ROW()-2)),INDEX('⚙ Setup'!$B:$B,ROW()-2),0),0)} -> 0 | E26: =D26-C26 -> 0
A27: Subscriptions | C27: 75 | D27: {=IFERROR(IF(ISNUMBER(INDEX('⚙ Setup'!$B:$B,ROW()-2)),INDEX('⚙ Setup'!$B:$B,ROW()-2),0),0)} -> 0 | E27: =D27-C27 -> -75
A28: Pets | C28: 0 | D28: {=IFERROR(IF(ISNUMBER(INDEX('⚙ Setup'!$B:$B,ROW()-2)),INDEX('⚙ Setup'!$B:$B,ROW()-2),0),0)} -> 0 | E28: =D28-C28 -> 0
... A31: Miscellaneous | C31: 80 | D31: {=IFERROR(IF(ISNUMBER(INDEX('⚙ Setup'!$B:$B,ROW()-2)),INDEX('⚙ Setup'!$B:$B,ROW()-2),0),0)} -> 0 | E31: =D31-C31 -> -80
A32: TOTAL EXPENSES | C32: =SUM(C17:C31) -> 3395 | D32: =SUM(D17:D31) -> 0
A34: NET BALANCE | C34: =C13-C32 -> 1655

Sheet Feb
A1: ="📅 FEB "&'⚙ Setup'!$B$10&" · Monthly Budget" -> 📅 FEB 2026 · Monthly Budget
A2: INCOME | C2: EXPENSES | E2: NET
A3: =C4 -> 5050 | C3: =C5 -> 3330 | E3: =C4-C5 -> 1720
B4: Total Income | C4: =IFERROR(C13,0) -> 5050
B5: Total Expenses | C5: =IFERROR(C32,0) -> 3330
A6: Income
A7: Source | B7: Notes | C7: Amount | D7: Budget | E7: Difference
A8: Primary Salary | C8: =IFERROR('⚙ Setup'!$B$7,0) -> 5000 | D8: =IFERROR(IF(ISNUMBER('⚙ Setup'!$B$7),'⚙ Setup'!$B$7,0),0) -> 5000 | E8: =C8-D8 -> 0
A9: Secondary Income | C9: 0 | D9: 0 | E9: =C9-D9 -> 0
A10: Freelance / Side Hustle | C10: 0 | D10: 200 | E10: =C10-D10 -> -200
A11: Investment Income | C11: 50 | D11: 50 | E11: =C11-D11 -> 0
A12: Other Income | C12: 0 | D12: 0 | E12: =C12-D12 -> 0
A13: TOTAL INCOME | C13: =SUM(C8:C12) -> 5050 | D13: =SUM(D8:D12) -> 5250
A15: Expenses
A16: Category | B16: Notes | C16: Actual | D16: Budget | E16: Difference
A17: Housing | C17: 1500 | D17: {=IFERROR(IF(ISNUMBER(INDEX('⚙ Setup'!$B:$B,ROW()-2)),INDEX('⚙ Setup'!$B:$B,ROW()-2),0),0)} -> 0 | E17: =D17-C17 -> -1500
A18: Transportation | C18: 350 | D18: {=IFERROR(IF(ISNUMBER(INDEX('⚙ Setup'!$B:$B,ROW()-2)),INDEX('⚙ Setup'!$B:$B,ROW()-2),0),0)} -> 0 | E18: =D18-C18 -> -350
A19: Food & Groceries | C19: 610 | D19: {=IFERROR(IF(ISNUMBER(INDEX('⚙ Setup'!$B:$B,ROW()-2)),INDEX('⚙ Setup'!$B:$B,ROW()-2),0),0)} -> 0 | E19: =D19-C19 -> -610
A20: Utilities | C20: 195 | D20: {=IFERROR(IF(ISNUMBER(INDEX('⚙ Setup'!$B:$B,ROW()-2)),INDEX('⚙ Setup'!$B:$B,ROW()-2),0),0)} -> 0 | E20: =D20-C20 -> -195
A21: Insurance | C21: 250 | D21: {=IFERROR(IF(ISNUMBER(INDEX('⚙ Setup'!$B:$B,ROW()-2)),INDEX('⚙ Setup'!$B:$B,ROW()-2),0),0)} -> 0 | E21: =D21-C21 -> -250
A22: Healthcare | C22: 0 | D22: {=IFERROR(IF(ISNUMBER(INDEX('⚙ Setup'!$B:$B,ROW()-2)),INDEX('⚙ Setup'!$B:$B,ROW()-2),0),0)} -> 0 | E22: =D22-C22 -> 0
A23: Entertainment | C23: 80 | D23: {=IFERROR(IF(ISNUMBER(INDEX('⚙ Setup'!$B:$B,ROW()-2)),INDEX('⚙ Setup'!$B:$B,ROW()-2),0),0)} -> 0 | E23: =D23-C23 -> -80
A24: Clothing | C24: 120 | D24: {=IFERROR(IF(ISNUMBER(INDEX('⚙ Setup'!$B:$B,ROW()-2)),INDEX('⚙ Setup'!$B:$B,ROW()-2),0),0)} -> 0 | E24: =D24-C24 -> -120
A25: Personal Care | C25: 60 | D25: {=IFERROR(IF(ISNUMBER(INDEX('⚙ Setup'!$B:$B,ROW()-2)),INDEX('⚙ Setup'!$B:$B,ROW()-2),0),0)} -> 0 | E25: =D25-C25 -> -60
A26: Education | C26: 0 | D26: {=IFERROR(IF(ISNUMBER(INDEX('⚙ Setup'!$B:$B,ROW()-2)),INDEX('⚙ Setup'!$B:$B,ROW()-2),0),0)} -> 0 | E26: =D26-C26 -> 0
A27: Subscriptions | C27: 75 | D27: {=IFERROR(IF(ISNUMBER(INDEX('⚙ Setup'!$B:$B,ROW()-2)),INDEX('⚙ Setup'!$B:$B,ROW()-2),0),0)} -> 0 | E27: =D27-C27 -> -75
A28: Pets | C28: 0 | D28: {=IFERROR(IF(ISNUMBER(INDEX('⚙ Setup'!$B:$B,ROW()-2)),INDEX('⚙ Setup'!$B:$B,ROW()-2),0),0)} -> 0 | E28: =D28-C28 -> 0
... A31: Miscellaneous | C31: 60 | D31: {=IFERROR(IF(ISNUMBER(INDEX('⚙ Setup'!$B:$B,ROW()-2)),INDEX('⚙ Setup'!$B:$B,ROW()-2),0),0)} -> 0 | E31: =D31-C31 -> -60
A32: TOTAL EXPENSES | C32: =SUM(C17:C31) -> 3330 | D32: =SUM(D17:D31) -> 0
A34: NET BALANCE | C34: =C13-C32 -> 1720

Sheet Mar
A1: ="📅 MAR "&'⚙ Setup'!$B$10&" · Monthly Budget" -> 📅 MAR 2026 · Monthly Budget
A2: INCOME | C2: EXPENSES | E2: NET
A3: =C4 -> 5050 | C3: =C5 -> 3560 | E3: =C4-C5 -> 1490
B4: Total Income | C4: =IFERROR(C13,0) -> 5050
B5: Total Expenses | C5: =IFERROR(C32,0) -> 3560
A6: Income
A7: Source | B7: Notes | C7: Amount | D7: Budget | E7: Difference
A8: Primary Salary | C8: =IFERROR('⚙ Setup'!$B$7,0) -> 5000 | D8: =IFERROR(IF(ISNUMBER('⚙ Setup'!$B$7),'⚙ Setup'!$B$7,0),0) -> 5000 | E8: =C8-D8 -> 0
A9: Secondary Income | C9: 0 | D9: 0 | E9: =C9-D9 -> 0
A10: Freelance / Side Hustle | C10: 0 | D10: 200 | E10: =C10-D10 -> -200
A11: Investment Income | C11: 50 | D11: 50 | E11: =C11-D11 -> 0
A12: Other Income | C12: 0 | D12: 0 | E12: =C12-D12 -> 0
A13: TOTAL INCOME | C13: =SUM(C8:C12) -> 5050 | D13: =SUM(D8:D12) -> 5250
A15: Expenses
A16: Category | B16: Notes | C16: Actual | D16: Budget | E16: Difference
A17: Housing | C17: 1500 | D17: {=IFERROR(IF(ISNUMBER(INDEX('⚙ Setup'!$B:$B,ROW()-2)),INDEX('⚙ Setup'!$B:$B,ROW()-2),0),0)} -> 0 | E17: =D17-C17 -> -1500
A18: Transportation | C18: 350 | D18: {=IFERROR(IF(ISNUMBER(INDEX('⚙ Setup'!$B:$B,ROW()-2)),INDEX('⚙ Setup'!$B:$B,ROW()-2),0),0)} -> 0 | E18: =D18-C18 -> -350
A19: Food & Groceries | C19: 590 | D19: {=IFERROR(IF(ISNUMBER(INDEX('⚙ Setup'!$B:$B,ROW()-2)),INDEX('⚙ Setup'!$B:$B,ROW()-2),0),0)} -> 0 | E19: =D19-C19 -> -590
A20: Utilities | C20: 175 | D20: {=IFERROR(IF(ISNUMBER(INDEX('⚙ Setup'!$B:$B,ROW()-2)),INDEX('⚙ Setup'!$B:$B,ROW()-2),0),0)} -> 0 | E20: =D20-C20 -> -175
A21: Insurance | C21: 250 | D21: {=IFERROR(IF(ISNUMBER(INDEX('⚙ Setup'!$B:$B,ROW()-2)),INDEX('⚙ Setup'!$B:$B,ROW()-2),0),0)} -> 0 | E21: =D21-C21 -> -250
A22: Healthcare | C22: 100 | D22: {=IFERROR(IF(ISNUMBER(INDEX('⚙ Setup'!$B:$B,ROW()-2)),INDEX('⚙ Setup'!$B:$B,ROW()-2),0),0)} -> 0 | E22: =D22-C22 -> -100
A23: Entertainment | C23: 100 | D23: {=IFERROR(IF(ISNUMBER(INDEX('⚙ Setup'!$B:$B,ROW()-2)),INDEX('⚙ Setup'!$B:$B,ROW()-2),0),0)} -> 0 | E23: =D23-C23 -> -100
A24: Clothing | C24: 80 | D24: {=IFERROR(IF(ISNUMBER(INDEX('⚙ Setup'!$B:$B,ROW()-2)),INDEX('⚙ Setup'!$B:$B,ROW()-2),0),0)} -> 0 | E24: =D24-C24 -> -80
A25: Personal Care | C25: 60 | D25: {=IFERROR(IF(ISNUMBER(INDEX('⚙ Setup'!$B:$B,ROW()-2)),INDEX('⚙ Setup'!$B:$B,ROW()-2),0),0)} -> 0 | E25: =D25-C25 -> -60
A26: Education | C26: 0 | D26: {=IFERROR(IF(ISNUMBER(INDEX('⚙ Setup'!$B:$B,ROW()-2)),INDEX('⚙ Setup'!$B:$B,ROW()-2),0),0)} -> 0 | E26: =D26-C26 -> 0
A27: Subscriptions | C27: 75 | D27: {=IFERROR(IF(ISNUMBER(INDEX('⚙ Setup'!$B:$B,ROW()-2)),INDEX('⚙ Setup'!$B:$B,ROW()-2),0),0)} -> 0 | E27: =D27-C27 -> -75
A28: Pets | C28: 0 | D28: {=IFERROR(IF(ISNUMBER(INDEX('⚙ Setup'!$B:$B,ROW()-2)),INDEX('⚙ Setup'!$B:$B,ROW()-2),0),0)} -> 0 | E28: =D28-C28 -> 0
... A31: Miscellaneous | C31: 80 | D31: {=IFERROR(IF(ISNUMBER(INDEX('⚙ Setup'!$B:$B,ROW()-2)),INDEX('⚙ Setup'!$B:$B,ROW()-2),0),0)} -> 0 | E31: =D31-C31 -> -80
A32: TOTAL EXPENSES | C32: =SUM(C17:C31) -> 3560 | D32: =SUM(D17:D31) -> 0
A34: NET BALANCE | C34: =C13-C32 -> 1490

Sheet Apr
A1: ="📅 APR "&'⚙ Setup'!$B$10&" · Monthly Budget" -> 📅 APR 2026 · Monthly Budget
A2: INCOME | C2: EXPENSES | E2: NET
A3: =C4 -> 5580 | C3: =C5 -> 3685 | E3: =C4-C5 -> 1895
B4: Total Income | C4: =IFERROR(C13,0) -> 5580
B5: Total Expenses | C5: =IFERROR(C32,0) -> 3685
A6: Income
A7: Source | B7: Notes | C7: Amount | D7: Budget | E7: Difference
A8: Primary Salary | C8: =IFERROR('⚙ Setup'!$B$7,0) -> 5000 | D8: =IFERROR(IF(ISNUMBER('⚙ Setup'!$B$7),'⚙ Setup'!$B$7,0),0) -> 5000 | E8: =C8-D8 -> 0
A9: Secondary Income | C9: 0 | D9: 0 | E9: =C9-D9 -> 0
A10: Freelance / Side Hustle | C10: 500 | D10: 200 | E10: =C10-D10 -> 300
A11: Investment Income | C11: 80 | D11: 50 | E11: =C11-D11 -> 30
A12: Other Income | C12: 0 | D12: 0 | E12: =C12-D12 -> 0
A13: TOTAL INCOME | C13: =SUM(C8:C12) -> 5580 | D13: =SUM(D8:D12) -> 5250
A15: Expenses
A16: Category | B16: Notes | C16: Actual | D16: Budget | E16: Difference
A17: Housing | C17: 1500 | D17: {=IFERROR(IF(ISNUMBER(INDEX('⚙ Setup'!$B:$B,ROW()-2)),INDEX('⚙ Setup'!$B:$B,ROW()-2),0),0)} -> 0 | E17: =D17-C17 -> -1500
A18: Transportation | C18: 350 | D18: {=IFERROR(IF(ISNUMBER(INDEX('⚙ Setup'!$B:$B,ROW()-2)),INDEX('⚙ Setup'!$B:$B,ROW()-2),0),0)} -> 0 | E18: =D18-C18 -> -350
A19: Food & Groceries | C19: 620 | D19: {=IFERROR(IF(ISNUMBER(INDEX('⚙ Setup'!$B:$B,ROW()-2)),INDEX('⚙ Setup'!$B:$B,ROW()-2),0),0)} -> 0 | E19: =D19-C19 -> -620
A20: Utilities | C20: 160 | D20: {=IFERROR(IF(ISNUMBER(INDEX('⚙ Setup'!$B:$B,ROW()-2)),INDEX('⚙ Setup'!$B:$B,ROW()-2),0),0)} -> 0 | E20: =D20-C20 -> -160
A21: Insurance | C21: 250 | D21: {=IFERROR(IF(ISNUMBER(INDEX('⚙ Setup'!$B:$B,ROW()-2)),INDEX('⚙ Setup'!$B:$B,ROW()-2),0),0)} -> 0 | E21: =D21-C21 -> -250
A22: Healthcare | C22: 80 | D22: {=IFERROR(IF(ISNUMBER(INDEX('⚙ Setup'!$B:$B,ROW()-2)),INDEX('⚙ Setup'!$B:$B,ROW()-2),0),0)} -> 0 | E22: =D22-C22 -> -80
A23: Entertainment | C23: 150 | D23: {=IFERROR(IF(ISNUMBER(INDEX('⚙ Setup'!$B:$B,ROW()-2)),INDEX('⚙ Setup'!$B:$B,ROW()-2),0),0)} -> 0 | E23: =D23-C23 -> -150
A24: Clothing | C24: 200 | D24: {=IFERROR(IF(ISNUMBER(INDEX('⚙ Setup'!$B:$B,ROW()-2)),INDEX('⚙ Setup'!$B:$B,ROW()-2),0),0)} -> 0 | E24: =D24-C24 -> -200
A25: Personal Care | C25: 60 | D25: {=IFERROR(IF(ISNUMBER(INDEX('⚙ Setup'!$B:$B,ROW()-2)),INDEX('⚙ Setup'!$B:$B,ROW()-2),0),0)} -> 0 | E25: =D25-C25 -> -60
A26: Education | C26: 50 | D26: {=IFERROR(IF(ISNUMBER(INDEX('⚙ Setup'!$B:$B,ROW()-2)),INDEX('⚙ Setup'!$B:$B,ROW()-2),0),0)} -> 0 | E26: =D26-C26 -> -50
A27: Subscriptions | C27: 75 | D27: {=IFERROR(IF(ISNUMBER(INDEX('⚙ Setup'!$B:$B,ROW()-2)),INDEX('⚙ Setup'!$B:$B,ROW()-2),0),0)} -> 0 | E27: =D27-C27 -> -75
A28: Pets | C28: 0 | D28: {=IFERROR(IF(ISNUMBER(INDEX('⚙ Setup'!$B:$B,ROW()-2)),INDEX('⚙ Setup'!$B:$B,ROW()-2),0),0)} -> 0 | E28: =D28-C28 -> 0
... A31: Miscellaneous | C31: 90 | D31: {=IFERROR(IF(ISNUMBER(INDEX('⚙ Setup'!$B:$B,ROW()-2)),INDEX('⚙ Setup'!$B:$B,ROW()-2),0),0)} -> 0 | E31: =D31-C31 -> -90
A32: TOTAL EXPENSES | C32: =SUM(C17:C31) -> 3685 | D32: =SUM(D17:D31) -> 0
A34: NET BALANCE | C34: =C13-C32 -> 1895

Sheet May
A1: ="📅 MAY "&'⚙ Setup'!$B$10&" · Monthly Budget" -> 📅 MAY 2026 · Monthly Budget
A2: INCOME | C2: EXPENSES | E2: NET
A3: =C4 -> 5580 | C3: =C5 -> 3790 | E3: =C4-C5 -> 1790
B4: Total Income | C4: =IFERROR(C13,0) -> 5580
B5: Total Expenses | C5: =IFERROR(C32,0) -> 3790
A6: Income
A7: Source | B7: Notes | C7: Amount | D7: Budget | E7: Difference
A8: Primary Salary | C8: =IFERROR('⚙ Setup'!$B$7,0) -> 5000 | D8: =IFERROR(IF(ISNUMBER('⚙ Setup'!$B$7),'⚙ Setup'!$B$7,0),0) -> 5000 | E8: =C8-D8 -> 0
A9: Secondary Income | C9: 0 | D9: 0 | E9: =C9-D9 -> 0
A10: Freelance / Side Hustle | C10: 500 | D10: 200 | E10: =C10-D10 -> 300
A11: Investment Income | C11: 80 | D11: 50 | E11: =C11-D11 -> 30
A12: Other Income | C12: 0 | D12: 0 | E12: =C12-D12 -> 0
A13: TOTAL INCOME | C13: =SUM(C8:C12) -> 5580 | D13: =SUM(D8:D12) -> 5250
A15: Expenses
A16: Category | B16: Notes | C16: Actual | D16: Budget | E16: Difference
A17: Housing | C17: 1500 | D17: {=IFERROR(IF(ISNUMBER(INDEX('⚙ Setup'!$B:$B,ROW()-2)),INDEX('⚙ Setup'!$B:$B,ROW()-2),0),0)} -> 0 | E17: =D17-C17 -> -1500
A18: Transportation | C18: 380 | D18: {=IFERROR(IF(ISNUMBER(INDEX('⚙ Setup'!$B:$B,ROW()-2)),INDEX('⚙ Setup'!$B:$B,ROW()-2),0),0)} -> 0 | E18: =D18-C18 -> -380
A19: Food & Groceries | C19: 640 | D19: {=IFERROR(IF(ISNUMBER(INDEX('⚙ Setup'!$B:$B,ROW()-2)),INDEX('⚙ Setup'!$B:$B,ROW()-2),0),0)} -> 0 | E19: =D19-C19 -> -640
A20: Utilities | C20: 155 | D20: {=IFERROR(IF(ISNUMBER(INDEX('⚙ Setup'!$B:$B,ROW()-2)),INDEX('⚙ Setup'!$B:$B,ROW()-2),0),0)} -> 0 | E20: =D20-C20 -> -155
A21: Insurance | C21: 250 | D21: {=IFERROR(IF(ISNUMBER(INDEX('⚙ Setup'!$B:$B,ROW()-2)),INDEX('⚙ Setup'!$B:$B,ROW()-2),0),0)} -> 0 | E21: =D21-C21 -> -250
A22: Healthcare | C22: 0 | D22: {=IFERROR(IF(ISNUMBER(INDEX('⚙ Setup'!$B:$B,ROW()-2)),INDEX('⚙ Setup'!$B:$B,ROW()-2),0),0)} -> 0 | E22: =D22-C22 -> 0
A23: Entertainment | C23: 180 | D23: {=IFERROR(IF(ISNUMBER(INDEX('⚙ Setup'!$B:$B,ROW()-2)),INDEX('⚙ Setup'!$B:$B,ROW()-2),0),0)} -> 0 | E23: =D23-C23 -> -180
A24: Clothing | C24: 150 | D24: {=IFERROR(IF(ISNUMBER(INDEX('⚙ Setup'!$B:$B,ROW()-2)),INDEX('⚙ Setup'!$B:$B,ROW()-2),0),0)} -> 0 | E24: =D24-C24 -> -150
A25: Personal Care | C25: 60 | D25: {=IFERROR(IF(ISNUMBER(INDEX('⚙ Setup'!$B:$B,ROW()-2)),INDEX('⚙ Setup'!$B:$B,ROW()-2),0),0)} -> 0 | E25: =D25-C25 -> -60
A26: Education | C26: 50 | D26: {=IFERROR(IF(ISNUMBER(INDEX('⚙ Setup'!$B:$B,ROW()-2)),INDEX('⚙ Setup'!$B:$B,ROW()-2),0),0)} -> 0 | E26: =D26-C26 -> -50
A27: Subscriptions | C27: 75 | D27: {=IFERROR(IF(ISNUMBER(INDEX('⚙ Setup'!$B:$B,ROW()-2)),INDEX('⚙ Setup'!$B:$B,ROW()-2),0),0)} -> 0 | E27: =D27-C27 -> -75
A28: Pets | C28: 0 | D28: {=IFERROR(IF(ISNUMBER(INDEX('⚙ Setup'!$B:$B,ROW()-2)),INDEX('⚙ Setup'!$B:$B,ROW()-2),0),0)} -> 0 | E28: =D28-C28 -> 0
... A31: Miscellaneous | C31: 100 | D31: {=IFERROR(IF(ISNUMBER(INDEX('⚙ Setup'!$B:$B,ROW()-2)),INDEX('⚙ Setup'!$B:$B,ROW()-2),0),0)} -> 0 | E31: =D31-C31 -> -100
A32: TOTAL EXPENSES | C32: =SUM(C17:C31) -> 3790 | D32: =SUM(D17:D31) -> 0
A34: NET BALANCE | C34: =C13-C32 -> 1790

Sheet Jun
A1: ="📅 JUN "&'⚙ Setup'!$B$10&" · Monthly Budget" -> 📅 JUN 2026 · Monthly Budget
A2: INCOME | C2: EXPENSES | E2: NET
A3: =C4 -> 5080 | C3: =C5 -> 4375 | E3: =C4-C5 -> 705
B4: Total Income | C4: =IFERROR(C13,0) -> 5080
B5: Total Expenses | C5: =IFERROR(C32,0) -> 4375
A6: Income
A7: Source | B7: Notes | C7: Amount | D7: Budget | E7: Difference
A8: Primary Salary | C8: =IFERROR('⚙ Setup'!$B$7,0) -> 5000 | D8: =IFERROR(IF(ISNUMBER('⚙ Setup'!$B$7),'⚙ Setup'!$B$7,0),0) -> 5000 | E8: =C8-D8 -> 0
A9: Secondary Income | C9: 0 | D9: 0 | E9: =C9-D9 -> 0
A10: Freelance / Side Hustle | C10: 0 | D10: 200 | E10: =C10-D10 -> -200
A11: Investment Income | C11: 80 | D11: 50 | E11: =C11-D11 -> 30
A12: Other Income | C12: 0 | D12: 0 | E12: =C12-D12 -> 0
A13: TOTAL INCOME | C13: =SUM(C8:C12) -> 5080 | D13: =SUM(D8:D12) -> 5250
A15: Expenses
A16: Category | B16: Notes | C16: Actual | D16: Budget | E16: Difference
A17: Housing | C17: 1500 | D17: {=IFERROR(IF(ISNUMBER(INDEX('⚙ Setup'!$B:$B,ROW()-2)),INDEX('⚙ Setup'!$B:$B,ROW()-2),0),0)} -> 0 | E17: =D17-C17 -> -1500
A18: Transportation | C18: 360 | D18: {=IFERROR(IF(ISNUMBER(INDEX('⚙ Setup'!$B:$B,ROW()-2)),INDEX('⚙ Setup'!$B:$B,ROW()-2),0),0)} -> 0 | E18: =D18-C18 -> -360
A19: Food & Groceries | C19: 700 | D19: {=IFERROR(IF(ISNUMBER(INDEX('⚙ Setup'!$B:$B,ROW()-2)),INDEX('⚙ Setup'!$B:$B,ROW()-2),0),0)} -> 0 | E19: =D19-C19 -> -700
A20: Utilities | C20: 140 | D20: {=IFERROR(IF(ISNUMBER(INDEX('⚙ Setup'!$B:$B,ROW()-2)),INDEX('⚙ Setup'!$B:$B,ROW()-2),0),0)} -> 0 | E20: =D20-C20 -> -140
A21: Insurance | C21: 250 | D21: {=IFERROR(IF(ISNUMBER(INDEX('⚙ Setup'!$B:$B,ROW()-2)),INDEX('⚙ Setup'!$B:$B,ROW()-2),0),0)} -> 0 | E21: =D21-C21 -> -250
A22: Healthcare | C22: 120 | D22: {=IFERROR(IF(ISNUMBER(INDEX('⚙ Setup'!$B:$B,ROW()-2)),INDEX('⚙ Setup'!$B:$B,ROW()-2),0),0)} -> 0 | E22: =D22-C22 -> -120
A23: Entertainment | C23: 200 | D23: {=IFERROR(IF(ISNUMBER(INDEX('⚙ Setup'!$B:$B,ROW()-2)),INDEX('⚙ Setup'!$B:$B,ROW()-2),0),0)} -> 0 | E23: =D23-C23 -> -200
A24: Clothing | C24: 0 | D24: {=IFERROR(IF(ISNUMBER(INDEX('⚙ Setup'!$B:$B,ROW()-2)),INDEX('⚙ Setup'!$B:$B,ROW()-2),0),0)} -> 0 | E24: =D24-C24 -> 0
A25: Personal Care | C25: 80 | D25: {=IFERROR(IF(ISNUMBER(INDEX('⚙ Setup'!$B:$B,ROW()-2)),INDEX('⚙ Setup'!$B:$B,ROW()-2),0),0)} -> 0 | E25: =D25-C25 -> -80
A26: Education | C26: 0 | D26: {=IFERROR(IF(ISNUMBER(INDEX('⚙ Setup'!$B:$B,ROW()-2)),INDEX('⚙ Setup'!$B:$B,ROW()-2),0),0)} -> 0 | E26: =D26-C26 -> 0
A27: Subscriptions | C27: 75 | D27: {=IFERROR(IF(ISNUMBER(INDEX('⚙ Setup'!$B:$B,ROW()-2)),INDEX('⚙ Setup'!$B:$B,ROW()-2),0),0)} -> 0 | E27: =D27-C27 -> -75
A28: Pets | C28: 0 | D28: {=IFERROR(IF(ISNUMBER(INDEX('⚙ Setup'!$B:$B,ROW()-2)),INDEX('⚙ Setup'!$B:$B,ROW()-2),0),0)} -> 0 | E28: =D28-C28 -> 0
... A31: Miscellaneous | C31: 120 | D31: {=IFERROR(IF(ISNUMBER(INDEX('⚙ Setup'!$B:$B,ROW()-2)),INDEX('⚙ Setup'!$B:$B,ROW()-2),0),0)} -> 0 | E31: =D31-C31 -> -120
A32: TOTAL EXPENSES | C32: =SUM(C17:C31) -> 4375 | D32: =SUM(D17:D31) -> 0
A34: NET BALANCE | C34: =C13-C32 -> 705

Sheet Jul
A1: ="📅 JUL "&'⚙ Setup'!$B$10&" · Monthly Budget" -> 📅 JUL 2026 · Monthly Budget
A2: INCOME | C2: EXPENSES | E2: NET
A3: =C4 -> 5880 | C3: =C5 -> 3430 | E3: =C4-C5 -> 2450
B4: Total Income | C4: =IFERROR(C13,0) -> 5880
B5: Total Expenses | C5: =IFERROR(C32,0) -> 3430
A6: Income
A7: Source | B7: Notes | C7: Amount | D7: Budget | E7: Difference
A8: Primary Salary | C8: =IFERROR('⚙ Setup'!$B$7,0) -> 5000 | D8: =IFERROR(IF(ISNUMBER('⚙ Setup'!$B$7),'⚙ Setup'!$B$7,0),0) -> 5000 | E8: =C8-D8 -> 0
A9: Secondary Income | C9: 0 | D9: 0 | E9: =C9-D9 -> 0
A10: Freelance / Side Hustle | C10: 800 | D10: 200 | E10: =C10-D10 -> 600
A11: Investment Income | C11: 80 | D11: 50 | E11: =C11-D11 -> 30
A12: Other Income | C12: 0 | D12: 0 | E12: =C12-D12 -> 0
A13: TOTAL INCOME | C13: =SUM(C8:C12) -> 5880 | D13: =SUM(D8:D12) -> 5250
A15: Expenses
A16: Category | B16: Notes | C16: Actual | D16: Budget | E16: Difference
A17: Housing | C17: 1500 | D17: {=IFERROR(IF(ISNUMBER(INDEX('⚙ Setup'!$B:$B,ROW()-2)),INDEX('⚙ Setup'!$B:$B,ROW()-2),0),0)} -> 0 | E17: =D17-C17 -> -1500
A18: Transportation | C18: 330 | D18: {=IFERROR(IF(ISNUMBER(INDEX('⚙ Setup'!$B:$B,ROW()-2)),INDEX('⚙ Setup'!$B:$B,ROW()-2),0),0)} -> 0 | E18: =D18-C18 -> -330
A19: Food & Groceries | C19: 680 | D19: {=IFERROR(IF(ISNUMBER(INDEX('⚙ Setup'!$B:$B,ROW()-2)),INDEX('⚙ Setup'!$B:$B,ROW()-2),0),0)} -> 0 | E19: =D19-C19 -> -680
A20: Utilities | C20: 130 | D20: {=IFERROR(IF(ISNUMBER(INDEX('⚙ Setup'!$B:$B,ROW()-2)),INDEX('⚙ Setup'!$B:$B,ROW()-2),0),0)} -> 0 | E20: =D20-C20 -> -130
A21: Insurance | C21: 250 | D21: {=IFERROR(IF(ISNUMBER(INDEX('⚙ Setup'!$B:$B,ROW()-2)),INDEX('⚙ Setup'!$B:$B,ROW()-2),0),0)} -> 0 | E21: =D21-C21 -> -250
A22: Healthcare | C22: 0 | D22: {=IFERROR(IF(ISNUMBER(INDEX('⚙ Setup'!$B:$B,ROW()-2)),INDEX('⚙ Setup'!$B:$B,ROW()-2),0),0)} -> 0 | E22: =D22-C22 -> 0
A23: Entertainment | C23: 160 | D23: {=IFERROR(IF(ISNUMBER(INDEX('⚙ Setup'!$B:$B,ROW()-2)),INDEX('⚙ Setup'!$B:$B,ROW()-2),0),0)} -> 0 | E23: =D23-C23 -> -160
A24: Clothing | C24: 80 | D24: {=IFERROR(IF(ISNUMBER(INDEX('⚙ Setup'!$B:$B,ROW()-2)),INDEX('⚙ Setup'!$B:$B,ROW()-2),0),0)} -> 0 | E24: =D24-C24 -> -80
A25: Personal Care | C25: 75 | D25: {=IFERROR(IF(ISNUMBER(INDEX('⚙ Setup'!$B:$B,ROW()-2)),INDEX('⚙ Setup'!$B:$B,ROW()-2),0),0)} -> 0 | E25: =D25-C25 -> -75
A26: Education | C26: 0 | D26: {=IFERROR(IF(ISNUMBER(INDEX('⚙ Setup'!$B:$B,ROW()-2)),INDEX('⚙ Setup'!$B:$B,ROW()-2),0),0)} -> 0 | E26: =D26-C26 -> 0
A27: Subscriptions | C27: 75 | D27: {=IFERROR(IF(ISNUMBER(INDEX('⚙ Setup'!$B:$B,ROW()-2)),INDEX('⚙ Setup'!$B:$B,ROW()-2),0),0)} -> 0 | E27: =D27-C27 -> -75
A28: Pets | C28: 0 | D28: {=IFERROR(IF(ISNUMBER(INDEX('⚙ Setup'!$B:$B,ROW()-2)),INDEX('⚙ Setup'!$B:$B,ROW()-2),0),0)} -> 0 | E28: =D28-C28 -> 0
... A31: Miscellaneous | C31: 100 | D31: {=IFERROR(IF(ISNUMBER(INDEX('⚙ Setup'!$B:$B,ROW()-2)),INDEX('⚙ Setup'!$B:$B,ROW()-2),0),0)} -> 0 | E31: =D31-C31 -> -100
A32: TOTAL EXPENSES | C32: =SUM(C17:C31) -> 3430 | D32: =SUM(D17:D31) -> 0
A34: NET BALANCE | C34: =C13-C32 -> 2450

Sheet Aug
A1: ="📅 AUG "&'⚙ Setup'!$B$10&" · Monthly Budget" -> 📅 AUG 2026 · Monthly Budget
A2: INCOME | C2: EXPENSES | E2: NET
A3: =C4 -> 5080 | C3: =C5 -> 3980 | E3: =C4-C5 -> 1100
B4: Total Income | C4: =IFERROR(C13,0) -> 5080
B5: Total Expenses | C5: =IFERROR(C32,0) -> 3980
A6: Income
A7: Source | B7: Notes | C7: Amount | D7: Budget | E7: Difference
A8: Primary Salary | C8: =IFERROR('⚙ Setup'!$B$7,0) -> 5000 | D8: =IFERROR(IF(ISNUMBER('⚙ Setup'!$B$7),'⚙ Setup'!$B$7,0),0) -> 5000 | E8: =C8-D8 -> 0
A9: Secondary Income | C9: 0 | D9: 0 | E9: =C9-D9 -> 0
A10: Freelance / Side Hustle | C10: 0 | D10: 200 | E10: =C10-D10 -> -200
A11: Investment Income | C11: 80 | D11: 50 | E11: =C11-D11 -> 30
A12: Other Income | C12: 0 | D12: 0 | E12: =C12-D12 -> 0
A13: TOTAL INCOME | C13: =SUM(C8:C12) -> 5080 | D13: =SUM(D8:D12) -> 5250
A15: Expenses
A16: Category | B16: Notes | C16: Actual | D16: Budget | E16: Difference
A17: Housing | C17: 1500 | D17: {=IFERROR(IF(ISNUMBER(INDEX('⚙ Setup'!$B:$B,ROW()-2)),INDEX('⚙ Setup'!$B:$B,ROW()-2),0),0)} -> 0 | E17: =D17-C17 -> -1500
A18: Transportation | C18: 340 | D18: {=IFERROR(IF(ISNUMBER(INDEX('⚙ Setup'!$B:$B,ROW()-2)),INDEX('⚙ Setup'!$B:$B,ROW()-2),0),0)} -> 0 | E18: =D18-C18 -> -340
A19: Food & Groceries | C19: 650 | D19: {=IFERROR(IF(ISNUMBER(INDEX('⚙ Setup'!$B:$B,ROW()-2)),INDEX('⚙ Setup'!$B:$B,ROW()-2),0),0)} -> 0 | E19: =D19-C19 -> -650
A20: Utilities | C20: 135 | D20: {=IFERROR(IF(ISNUMBER(INDEX('⚙ Setup'!$B:$B,ROW()-2)),INDEX('⚙ Setup'!$B:$B,ROW()-2),0),0)} -> 0 | E20: =D20-C20 -> -135
A21: Insurance | C21: 250 | D21: {=IFERROR(IF(ISNUMBER(INDEX('⚙ Setup'!$B:$B,ROW()-2)),INDEX('⚙ Setup'!$B:$B,ROW()-2),0),0)} -> 0 | E21: =D21-C21 -> -250
A22: Healthcare | C22: 100 | D22: {=IFERROR(IF(ISNUMBER(INDEX('⚙ Setup'!$B:$B,ROW()-2)),INDEX('⚙ Setup'!$B:$B,ROW()-2),0),0)} -> 0 | E22: =D22-C22 -> -100
A23: Entertainment | C23: 140 | D23: {=IFERROR(IF(ISNUMBER(INDEX('⚙ Setup'!$B:$B,ROW()-2)),INDEX('⚙ Setup'!$B:$B,ROW()-2),0),0)} -> 0 | E23: =D23-C23 -> -140
A24: Clothing | C24: 200 | D24: {=IFERROR(IF(ISNUMBER(INDEX('⚙ Setup'!$B:$B,ROW()-2)),INDEX('⚙ Setup'!$B:$B,ROW()-2),0),0)} -> 0 | E24: =D24-C24 -> -200
A25: Personal Care | C25: 70 | D25: {=IFERROR(IF(ISNUMBER(INDEX('⚙ Setup'!$B:$B,ROW()-2)),INDEX('⚙ Setup'!$B:$B,ROW()-2),0),0)} -> 0 | E25: =D25-C25 -> -70
A26: Education | C26: 0 | D26: {=IFERROR(IF(ISNUMBER(INDEX('⚙ Setup'!$B:$B,ROW()-2)),INDEX('⚙ Setup'!$B:$B,ROW()-2),0),0)} -> 0 | E26: =D26-C26 -> 0
A27: Subscriptions | C27: 75 | D27: {=IFERROR(IF(ISNUMBER(INDEX('⚙ Setup'!$B:$B,ROW()-2)),INDEX('⚙ Setup'!$B:$B,ROW()-2),0),0)} -> 0 | E27: =D27-C27 -> -75
A28: Pets | C28: 0 | D28: {=IFERROR(IF(ISNUMBER(INDEX('⚙ Setup'!$B:$B,ROW()-2)),INDEX('⚙ Setup'!$B:$B,ROW()-2),0),0)} -> 0 | E28: =D28-C28 -> 0
... A31: Miscellaneous | C31: 90 | D31: {=IFERROR(IF(ISNUMBER(INDEX('⚙ Setup'!$B:$B,ROW()-2)),INDEX('⚙ Setup'!$B:$B,ROW()-2),0),0)} -> 0 | E31: =D31-C31 -> -90
A32: TOTAL EXPENSES | C32: =SUM(C17:C31) -> 3980 | D32: =SUM(D17:D31) -> 0
A34: NET BALANCE | C34: =C13-C32 -> 1100

Sheet Sep
A1: ="📅 SEP "&'⚙ Setup'!$B$10&" · Monthly Budget" -> 📅 SEP 2026 · Monthly Budget
A2: INCOME | C2: EXPENSES | E2: NET
A3: =C4 -> 5080 | C3: =C5 -> 3520 | E3: =C4-C5 -> 1560
B4: Total Income | C4: =IFERROR(C13,0) -> 5080
B5: Total Expenses | C5: =IFERROR(C32,0) -> 3520
A6: Income
A7: Source | B7: Notes | C7: Amount | D7: Budget | E7: Difference
A8: Primary Salary | C8: =IFERROR('⚙ Setup'!$B$7,0) -> 5000 | D8: =IFERROR(IF(ISNUMBER('⚙ Setup'!$B$7),'⚙ Setup'!$B$7,0),0) -> 5000 | E8: =C8-D8 -> 0
A9: Secondary Income | C9: 0 | D9: 0 | E9: =C9-D9 -> 0
A10: Freelance / Side Hustle | C10: 0 | D10: 200 | E10: =C10-D10 -> -200
A11: Investment Income | C11: 80 | D11: 50 | E11: =C11-D11 -> 30
A12: Other Income | C12: 0 | D12: 0 | E12: =C12-D12 -> 0
A13: TOTAL INCOME | C13: =SUM(C8:C12) -> 5080 | D13: =SUM(D8:D12) -> 5250
A15: Expenses
A16: Category | B16: Notes | C16: Actual | D16: Budget | E16: Difference
A17: Housing | C17: 1500 | D17: {=IFERROR(IF(ISNUMBER(INDEX('⚙ Setup'!$B:$B,ROW()-2)),INDEX('⚙ Setup'!$B:$B,ROW()-2),0),0)} -> 0 | E17: =D17-C17 -> -1500
A18: Transportation | C18: 350 | D18: {=IFERROR(IF(ISNUMBER(INDEX('⚙ Setup'!$B:$B,ROW()-2)),INDEX('⚙ Setup'!$B:$B,ROW()-2),0),0)} -> 0 | E18: =D18-C18 -> -350
A19: Food & Groceries | C19: 600 | D19: {=IFERROR(IF(ISNUMBER(INDEX('⚙ Setup'!$B:$B,ROW()-2)),INDEX('⚙ Setup'!$B:$B,ROW()-2),0),0)} -> 0 | E19: =D19-C19 -> -600
A20: Utilities | C20: 165 | D20: {=IFERROR(IF(ISNUMBER(INDEX('⚙ Setup'!$B:$B,ROW()-2)),INDEX('⚙ Setup'!$B:$B,ROW()-2),0),0)} -> 0 | E20: =D20-C20 -> -165
A21: Insurance | C21: 250 | D21: {=IFERROR(IF(ISNUMBER(INDEX('⚙ Setup'!$B:$B,ROW()-2)),INDEX('⚙ Setup'!$B:$B,ROW()-2),0),0)} -> 0 | E21: =D21-C21 -> -250
A22: Healthcare | C22: 80 | D22: {=IFERROR(IF(ISNUMBER(INDEX('⚙ Setup'!$B:$B,ROW()-2)),INDEX('⚙ Setup'!$B:$B,ROW()-2),0),0)} -> 0 | E22: =D22-C22 -> -80
A23: Entertainment | C23: 110 | D23: {=IFERROR(IF(ISNUMBER(INDEX('⚙ Setup'!$B:$B,ROW()-2)),INDEX('⚙ Setup'!$B:$B,ROW()-2),0),0)} -> 0 | E23: =D23-C23 -> -110
A24: Clothing | C24: 100 | D24: {=IFERROR(IF(ISNUMBER(INDEX('⚙ Setup'!$B:$B,ROW()-2)),INDEX('⚙ Setup'!$B:$B,ROW()-2),0),0)} -> 0 | E24: =D24-C24 -> -100
A25: Personal Care | C25: 60 | D25: {=IFERROR(IF(ISNUMBER(INDEX('⚙ Setup'!$B:$B,ROW()-2)),INDEX('⚙ Setup'!$B:$B,ROW()-2),0),0)} -> 0 | E25: =D25-C25 -> -60
A26: Education | C26: 100 | D26: {=IFERROR(IF(ISNUMBER(INDEX('⚙ Setup'!$B:$B,ROW()-2)),INDEX('⚙ Setup'!$B:$B,ROW()-2),0),0)} -> 0 | E26: =D26-C26 -> -100
A27: Subscriptions | C27: 75 | D27: {=IFERROR(IF(ISNUMBER(INDEX('⚙ Setup'!$B:$B,ROW()-2)),INDEX('⚙ Setup'!$B:$B,ROW()-2),0),0)} -> 0 | E27: =D27-C27 -> -75
A28: Pets | C28: 0 | D28: {=IFERROR(IF(ISNUMBER(INDEX('⚙ Setup'!$B:$B,ROW()-2)),INDEX('⚙ Setup'!$B:$B,ROW()-2),0),0)} -> 0 | E28: =D28-C28 -> 0
... A31: Miscellaneous | C31: 80 | D31: {=IFERROR(IF(ISNUMBER(INDEX('⚙ Setup'!$B:$B,ROW()-2)),INDEX('⚙ Setup'!$B:$B,ROW()-2),0),0)} -> 0 | E31: =D31-C31 -> -80
A32: TOTAL EXPENSES | C32: =SUM(C17:C31) -> 3520 | D32: =SUM(D17:D31) -> 0
A34: NET BALANCE | C34: =C13-C32 -> 1560

Sheet Oct
A1: ="📅 OCT "&'⚙ Setup'!$B$10&" · Monthly Budget" -> 📅 OCT 2026 · Monthly Budget
A2: INCOME | C2: EXPENSES | E2: NET
A3: =C4 -> 5380 | C3: =C5 -> 3560 | E3: =C4-C5 -> 1820
B4: Total Income | C4: =IFERROR(C13,0) -> 5380
B5: Total Expenses | C5: =IFERROR(C32,0) -> 3560
A6: Income
A7: Source | B7: Notes | C7: Amount | D7: Budget | E7: Difference
A8: Primary Salary | C8: =IFERROR('⚙ Setup'!$B$7,0) -> 5000 | D8: =IFERROR(IF(ISNUMBER('⚙ Setup'!$B$7),'⚙ Setup'!$B$7,0),0) -> 5000 | E8: =C8-D8 -> 0
A9: Secondary Income | C9: 0 | D9: 0 | E9: =C9-D9 -> 0
A10: Freelance / Side Hustle | C10: 300 | D10: 200 | E10: =C10-D10 -> 100
A11: Investment Income | C11: 80 | D11: 50 | E11: =C11-D11 -> 30
A12: Other Income | C12: 0 | D12: 0 | E12: =C12-D12 -> 0
A13: TOTAL INCOME | C13: =SUM(C8:C12) -> 5380 | D13: =SUM(D8:D12) -> 5250
A15: Expenses
A16: Category | B16: Notes | C16: Actual | D16: Budget | E16: Difference
A17: Housing | C17: 1500 | D17: {=IFERROR(IF(ISNUMBER(INDEX('⚙ Setup'!$B:$B,ROW()-2)),INDEX('⚙ Setup'!$B:$B,ROW()-2),0),0)} -> 0 | E17: =D17-C17 -> -1500
A18: Transportation | C18: 350 | D18: {=IFERROR(IF(ISNUMBER(INDEX('⚙ Setup'!$B:$B,ROW()-2)),INDEX('⚙ Setup'!$B:$B,ROW()-2),0),0)} -> 0 | E18: =D18-C18 -> -350
A19: Food & Groceries | C19: 610 | D19: {=IFERROR(IF(ISNUMBER(INDEX('⚙ Setup'!$B:$B,ROW()-2)),INDEX('⚙ Setup'!$B:$B,ROW()-2),0),0)} -> 0 | E19: =D19-C19 -> -610
A20: Utilities | C20: 175 | D20: {=IFERROR(IF(ISNUMBER(INDEX('⚙ Setup'!$B:$B,ROW()-2)),INDEX('⚙ Setup'!$B:$B,ROW()-2),0),0)} -> 0 | E20: =D20-C20 -> -175
A21: Insurance | C21: 250 | D21: {=IFERROR(IF(ISNUMBER(INDEX('⚙ Setup'!$B:$B,ROW()-2)),INDEX('⚙ Setup'!$B:$B,ROW()-2),0),0)} -> 0 | E21: =D21-C21 -> -250
A22: Healthcare | C22: 0 | D22: {=IFERROR(IF(ISNUMBER(INDEX('⚙ Setup'!$B:$B,ROW()-2)),INDEX('⚙ Setup'!$B:$B,ROW()-2),0),0)} -> 0 | E22: =D22-C22 -> 0
A23: Entertainment | C23: 130 | D23: {=IFERROR(IF(ISNUMBER(INDEX('⚙ Setup'!$B:$B,ROW()-2)),INDEX('⚙ Setup'!$B:$B,ROW()-2),0),0)} -> 0 | E23: =D23-C23 -> -130
A24: Clothing | C24: 150 | D24: {=IFERROR(IF(ISNUMBER(INDEX('⚙ Setup'!$B:$B,ROW()-2)),INDEX('⚙ Setup'!$B:$B,ROW()-2),0),0)} -> 0 | E24: =D24-C24 -> -150
A25: Personal Care | C25: 60 | D25: {=IFERROR(IF(ISNUMBER(INDEX('⚙ Setup'!$B:$B,ROW()-2)),INDEX('⚙ Setup'!$B:$B,ROW()-2),0),0)} -> 0 | E25: =D25-C25 -> -60
A26: Education | C26: 100 | D26: {=IFERROR(IF(ISNUMBER(INDEX('⚙ Setup'!$B:$B,ROW()-2)),INDEX('⚙ Setup'!$B:$B,ROW()-2),0),0)} -> 0 | E26: =D26-C26 -> -100
A27: Subscriptions | C27: 75 | D27: {=IFERROR(IF(ISNUMBER(INDEX('⚙ Setup'!$B:$B,ROW()-2)),INDEX('⚙ Setup'!$B:$B,ROW()-2),0),0)} -> 0 | E27: =D27-C27 -> -75
A28: Pets | C28: 0 | D28: {=IFERROR(IF(ISNUMBER(INDEX('⚙ Setup'!$B:$B,ROW()-2)),INDEX('⚙ Setup'!$B:$B,ROW()-2),0),0)} -> 0 | E28: =D28-C28 -> 0
... A31: Miscellaneous | C31: 80 | D31: {=IFERROR(IF(ISNUMBER(INDEX('⚙ Setup'!$B:$B,ROW()-2)),INDEX('⚙ Setup'!$B:$B,ROW()-2),0),0)} -> 0 | E31: =D31-C31 -> -80
A32: TOTAL EXPENSES | C32: =SUM(C17:C31) -> 3560 | D32: =SUM(D17:D31) -> 0
A34: NET BALANCE | C34: =C13-C32 -> 1820

Sheet Nov
A1: ="📅 NOV "&'⚙ Setup'!$B$10&" · Monthly Budget" -> 📅 NOV 2026 · Monthly Budget
A2: INCOME | C2: EXPENSES | E2: NET
A3: =C4 -> 5080 | C3: =C5 -> 4135 | E3: =C4-C5 -> 945
B4: Total Income | C4: =IFERROR(C13,0) -> 5080
B5: Total Expenses | C5: =IFERROR(C32,0) -> 4135
A6: Income
A7: Source | B7: Notes | C7: Amount | D7: Budget | E7: Difference
A8: Primary Salary | C8: =IFERROR('⚙ Setup'!$B$7,0) -> 5000 | D8: =IFERROR(IF(ISNUMBER('⚙ Setup'!$B$7),'⚙ Setup'!$B$7,0),0) -> 5000 | E8: =C8-D8 -> 0
A9: Secondary Income | C9: 0 | D9: 0 | E9: =C9-D9 -> 0
A10: Freelance / Side Hustle | C10: 0 | D10: 200 | E10: =C10-D10 -> -200
A11: Investment Income | C11: 80 | D11: 50 | E11: =C11-D11 -> 30
A12: Other Income | C12: 0 | D12: 0 | E12: =C12-D12 -> 0
A13: TOTAL INCOME | C13: =SUM(C8:C12) -> 5080 | D13: =SUM(D8:D12) -> 5250
A15: Expenses
A16: Category | B16: Notes | C16: Actual | D16: Budget | E16: Difference
A17: Housing | C17: 1500 | D17: {=IFERROR(IF(ISNUMBER(INDEX('⚙ Setup'!$B:$B,ROW()-2)),INDEX('⚙ Setup'!$B:$B,ROW()-2),0),0)} -> 0 | E17: =D17-C17 -> -1500
A18: Transportation | C18: 360 | D18: {=IFERROR(IF(ISNUMBER(INDEX('⚙ Setup'!$B:$B,ROW()-2)),INDEX('⚙ Setup'!$B:$B,ROW()-2),0),0)} -> 0 | E18: =D18-C18 -> -360
A19: Food & Groceries | C19: 700 | D19: {=IFERROR(IF(ISNUMBER(INDEX('⚙ Setup'!$B:$B,ROW()-2)),INDEX('⚙ Setup'!$B:$B,ROW()-2),0),0)} -> 0 | E19: =D19-C19 -> -700
A20: Utilities | C20: 190 | D20: {=IFERROR(IF(ISNUMBER(INDEX('⚙ Setup'!$B:$B,ROW()-2)),INDEX('⚙ Setup'!$B:$B,ROW()-2),0),0)} -> 0 | E20: =D20-C20 -> -190
A21: Insurance | C21: 250 | D21: {=IFERROR(IF(ISNUMBER(INDEX('⚙ Setup'!$B:$B,ROW()-2)),INDEX('⚙ Setup'!$B:$B,ROW()-2),0),0)} -> 0 | E21: =D21-C21 -> -250
A22: Healthcare | C22: 100 | D22: {=IFERROR(IF(ISNUMBER(INDEX('⚙ Setup'!$B:$B,ROW()-2)),INDEX('⚙ Setup'!$B:$B,ROW()-2),0),0)} -> 0 | E22: =D22-C22 -> -100
A23: Entertainment | C23: 180 | D23: {=IFERROR(IF(ISNUMBER(INDEX('⚙ Setup'!$B:$B,ROW()-2)),INDEX('⚙ Setup'!$B:$B,ROW()-2),0),0)} -> 0 | E23: =D23-C23 -> -180
A24: Clothing | C24: 300 | D24: {=IFERROR(IF(ISNUMBER(INDEX('⚙ Setup'!$B:$B,ROW()-2)),INDEX('⚙ Setup'!$B:$B,ROW()-2),0),0)} -> 0 | E24: =D24-C24 -> -300
A25: Personal Care | C25: 60 | D25: {=IFERROR(IF(ISNUMBER(INDEX('⚙ Setup'!$B:$B,ROW()-2)),INDEX('⚙ Setup'!$B:$B,ROW()-2),0),0)} -> 0 | E25: =D25-C25 -> -60
A26: Education | C26: 0 | D26: {=IFERROR(IF(ISNUMBER(INDEX('⚙ Setup'!$B:$B,ROW()-2)),INDEX('⚙ Setup'!$B:$B,ROW()-2),0),0)} -> 0 | E26: =D26-C26 -> 0
A27: Subscriptions | C27: 75 | D27: {=IFERROR(IF(ISNUMBER(INDEX('⚙ Setup'!$B:$B,ROW()-2)),INDEX('⚙ Setup'!$B:$B,ROW()-2),0),0)} -> 0 | E27: =D27-C27 -> -75
A28: Pets | C28: 0 | D28: {=IFERROR(IF(ISNUMBER(INDEX('⚙ Setup'!$B:$B,ROW()-2)),INDEX('⚙ Setup'!$B:$B,ROW()-2),0),0)} -> 0 | E28: =D28-C28 -> 0
... A31: Miscellaneous | C31: 120 | D31: {=IFERROR(IF(ISNUMBER(INDEX('⚙ Setup'!$B:$B,ROW()-2)),INDEX('⚙ Setup'!$B:$B,ROW()-2),0),0)} -> 0 | E31: =D31-C31 -> -120
A32: TOTAL EXPENSES | C32: =SUM(C17:C31) -> 4135 | D32: =SUM(D17:D31) -> 0
A34: NET BALANCE | C34: =C13-C32 -> 945

Sheet Dec
A1: ="📅 DEC "&'⚙ Setup'!$B$10&" · Monthly Budget" -> 📅 DEC 2026 · Monthly Budget
A2: INCOME | C2: EXPENSES | E2: NET
A3: =C4 -> 5080 | C3: =C5 -> 4835 | E3: =C4-C5 -> 245
B4: Total Income | C4: =IFERROR(C13,0) -> 5080
B5: Total Expenses | C5: =IFERROR(C32,0) -> 4835
A6: Income
A7: Source | B7: Notes | C7: Amount | D7: Budget | E7: Difference
A8: Primary Salary | C8: =IFERROR('⚙ Setup'!$B$7,0) -> 5000 | D8: =IFERROR(IF(ISNUMBER('⚙ Setup'!$B$7),'⚙ Setup'!$B$7,0),0) -> 5000 | E8: =C8-D8 -> 0
A9: Secondary Income | C9: 0 | D9: 0 | E9: =C9-D9 -> 0
A10: Freelance / Side Hustle | C10: 0 | D10: 200 | E10: =C10-D10 -> -200
A11: Investment Income | C11: 80 | D11: 50 | E11: =C11-D11 -> 30
A12: Other Income | C12: 0 | D12: 0 | E12: =C12-D12 -> 0
A13: TOTAL INCOME | C13: =SUM(C8:C12) -> 5080 | D13: =SUM(D8:D12) -> 5250
A15: Expenses
A16: Category | B16: Notes | C16: Actual | D16: Budget | E16: Difference
A17: Housing | C17: 1500 | D17: {=IFERROR(IF(ISNUMBER(INDEX('⚙ Setup'!$B:$B,ROW()-2)),INDEX('⚙ Setup'!$B:$B,ROW()-2),0),0)} -> 0 | E17: =D17-C17 -> -1500
A18: Transportation | C18: 380 | D18: {=IFERROR(IF(ISNUMBER(INDEX('⚙ Setup'!$B:$B,ROW()-2)),INDEX('⚙ Setup'!$B:$B,ROW()-2),0),0)} -> 0 | E18: =D18-C18 -> -380
A19: Food & Groceries | C19: 800 | D19: {=IFERROR(IF(ISNUMBER(INDEX('⚙ Setup'!$B:$B,ROW()-2)),INDEX('⚙ Setup'!$B:$B,ROW()-2),0),0)} -> 0 | E19: =D19-C19 -> -800
A20: Utilities | C20: 200 | D20: {=IFERROR(IF(ISNUMBER(INDEX('⚙ Setup'!$B:$B,ROW()-2)),INDEX('⚙ Setup'!$B:$B,ROW()-2),0),0)} -> 0 | E20: =D20-C20 -> -200
A21: Insurance | C21: 250 | D21: {=IFERROR(IF(ISNUMBER(INDEX('⚙ Setup'!$B:$B,ROW()-2)),INDEX('⚙ Setup'!$B:$B,ROW()-2),0),0)} -> 0 | E21: =D21-C21 -> -250
A22: Healthcare | C22: 50 | D22: {=IFERROR(IF(ISNUMBER(INDEX('⚙ Setup'!$B:$B,ROW()-2)),INDEX('⚙ Setup'!$B:$B,ROW()-2),0),0)} -> 0 | E22: =D22-C22 -> -50
A23: Entertainment | C23: 250 | D23: {=IFERROR(IF(ISNUMBER(INDEX('⚙ Setup'!$B:$B,ROW()-2)),INDEX('⚙ Setup'!$B:$B,ROW()-2),0),0)} -> 0 | E23: =D23-C23 -> -250
A24: Clothing | C24: 400 | D24: {=IFERROR(IF(ISNUMBER(INDEX('⚙ Setup'!$B:$B,ROW()-2)),INDEX('⚙ Setup'!$B:$B,ROW()-2),0),0)} -> 0 | E24: =D24-C24 -> -400
A25: Personal Care | C25: 80 | D25: {=IFERROR(IF(ISNUMBER(INDEX('⚙ Setup'!$B:$B,ROW()-2)),INDEX('⚙ Setup'!$B:$B,ROW()-2),0),0)} -> 0 | E25: =D25-C25 -> -80
A26: Education | C26: 0 | D26: {=IFERROR(IF(ISNUMBER(INDEX('⚙ Setup'!$B:$B,ROW()-2)),INDEX('⚙ Setup'!$B:$B,ROW()-2),0),0)} -> 0 | E26: =D26-C26 -> 0
A27: Subscriptions | C27: 75 | D27: {=IFERROR(IF(ISNUMBER(INDEX('⚙ Setup'!$B:$B,ROW()-2)),INDEX('⚙ Setup'!$B:$B,ROW()-2),0),0)} -> 0 | E27: =D27-C27 -> -75
A28: Pets | C28: 0 | D28: {=IFERROR(IF(ISNUMBER(INDEX('⚙ Setup'!$B:$B,ROW()-2)),INDEX('⚙ Setup'!$B:$B,ROW()-2),0),0)} -> 0 | E28: =D28-C28 -> 0
... A31: Miscellaneous | C31: 150 | D31: {=IFERROR(IF(ISNUMBER(INDEX('⚙ Setup'!$B:$B,ROW()-2)),INDEX('⚙ Setup'!$B:$B,ROW()-2),0),0)} -> 0 | E31: =D31-C31 -> -150
A32: TOTAL EXPENSES | C32: =SUM(C17:C31) -> 4835 | D32: =SUM(D17:D31) -> 0
A34: NET BALANCE | C34: =C13-C32 -> 245

Sheet 🗓 Bill Calendar
A1: 🗓 BILL CALENDAR — Monthly Payment Tracker
A3: Bill / Service | B3: Due Day | C3: Amount | D3: Frequency | E3: Auto-pay? | F3: Status | G3: Category
A4: Rent / Mortgage | B4: 1 | C4: 1500 | D4: Monthly | E4: Yes | F4: ✓ Paid | G4: Housing
A5: Electricity | B5: 5 | C5: 120 | D5: Monthly | E5: No | F5: ⏳ Pending | G5: Utilities
A6: Internet | B6: 8 | C6: 80 | D6: Monthly | E6: Yes | F6: ✓ Paid | G6: Utilities
A7: Car Payment | B7: 10 | C7: 350 | D7: Monthly | E7: Yes | F7: ✓ Paid | G7: Transportation
A8: Car Insurance | B8: 15 | C8: 180 | D8: Monthly | E8: Yes | F8: ✓ Paid | G8: Insurance
A9: Health Insurance | B9: 1 | C9: 220 | D9: Monthly | E9: Yes | F9: ✓ Paid | G9: Insurance
A10: Netflix | B10: 12 | C10: 17 | D10: Monthly | E10: Yes | F10: ✓ Paid | G10: Subscriptions
A11: Spotify | B11: 18 | C11: 11 | D11: Monthly | E11: Yes | F11: ✓ Paid | G11: Subscriptions
A12: Gym | B12: 1 | C12: 40 | D12: Monthly | E12: No | F12: ⏳ Pending | G12: Personal Care
A13: Student Loan | B13: 20 | C13: 250 | D13: Monthly | E13: No | F13: ⏳ Pending | G13: Education
A14: Credit Card Min | B14: 25 | C14: 150 | D14: Monthly | E14: No | F14: ✗ Late | G14: Debt
A15: Phone Bill | B15: 15 | C15: 85 | D15: Monthly | E15: Yes | F15: ✓ Paid | G15: Utilities
A16: MONTHLY TOTAL | C16: =SUM(C4:C15) -> 3003

Sheet 💳 Debt Tracker
A1: 💳 DEBT TRACKER — Snowball & Avalanche Methods
A2: Snowball = pay smallest balance first | Avalanche = pay highest APR first
A4: Debt Name | B4: Balance | C4: APR % | D4: Min Payment | E4: Extra Payment | F4: Total Payment | G4: Interest/Mo | H4: Months Left | I4: Payoff Date | J4: Method | K4: Priority
A5: Credit Card A | B5: 3200 | C5: 0.2499 | D5: 64 | E5: 0 | F5: =D5+E5 -> 64 | G5: =B5*C5/100/12 -> 0.6664 | H5: =IFERROR(NPER(C5/100/12,-F5,B5),0) -> 50.267367 | I5: =IFERROR(EDATE(TODAY(),INT(H5)),"N/A") -> 47708 | J5: Avalanche | K5: 1
A6: Credit Card B | B6: 1800 | C6: 0.1999 | D6: 36 | E6: 0 | F6: =D6+E6 -> 36 | G6: =B6*C6/100/12 -> 0.29985 | H6: =IFERROR(NPER(C6/100/12,-F6,B6),0) -> 50.213575 | I6: =IFERROR(EDATE(TODAY(),INT(H6)),"N/A") -> 47708 | J6: Snowball | K6: 2
A7: Student Loan | B7: 12000 | C7: 0.068 | D7: 138 | E7: 0 | F7: =D7+E7 -> 138 | G7: =B7*C7/100/12 -> 0.68 | H7: =IFERROR(NPER(C7/100/12,-F7,B7),0) -> 87.173939 | I7: =IFERROR(EDATE(TODAY(),INT(H7)),"N/A") -> 48835 | J7: Snowball | K7: 3
A8: Car Loan | B8: 8500 | C8: 0.075 | D8: 189 | E8: 0 | F8: =D8+E8 -> 189 | G8: =B8*C8/100/12 -> 0.53125 | H8: =IFERROR(NPER(C8/100/12,-F8,B8),0) -> 45.038278 | I8: =IFERROR(EDATE(TODAY(),INT(H8)),"N/A") -> 47555 | J8: Snowball | K8: 4
A9: Personal Loan | B9: 2500 | C9: 0.15 | D9: 75 | E9: 0 | F9: =D9+E9 -> 75 | G9: =B9*C9/100/12 -> 0.3125 | H9: =IFERROR(NPER(C9/100/12,-F9,B9),0) -> 33.405059 | I9: =IFERROR(EDATE(TODAY(),INT(H9)),"N/A") -> 47190 | J9: Snowball | K9: 5
A10: TOTAL | B10: =SUM(B5:B9) -> 28000 | D10: =SUM(D5:D9) -> 502 | F10: =SUM(F5:F9) -> 502 | G10: =SUM(G5:G9) -> 2.49
A12: 💡 Tip: Put extra $ into 'Extra Payment' column — recalculates automatically

Sheet 💰 Savings Tracker
A1: 💰 SAVINGS TRACKER — Goals & Sinking Funds
A3: Goal / Fund | B3: Target Amount | C3: Saved So Far | D3: Monthly Contribution | E3: Months to Goal | F3: % Complete | G3: Target Date | H3: Status
A4: Emergency Fund (3-6 mo) | B4: 15000 | C4: 4200 | D4: 500 | E4: =IFERROR((B4-C4)/D4,0) -> 21.6 | F4: =IFERROR(C4/B4,0) -> 0.28 | G4: =IFERROR(EDATE(TODAY(),INT(E4)),"Done") -> 46825 | H4: =IF(C4>=B4,"✅ Complete",IF(C4/B4>=0.75,"🔥 Almost!",IF(C4/B4>=0.5,"📈 Halfway","🚀 Building"))) -> 🚀 Building
A5: Vacation Fund | B5: 3000 | C5: 800 | D5: 200 | E5: =IFERROR((B5-C5)/D5,0) -> 11 | F5: =IFERROR(C5/B5,0) -> 0.26666667 | G5: =IFERROR(EDATE(TODAY(),INT(E5)),"Done") -> 46520 | H5: =IF(C5>=B5,"✅ Complete",IF(C5/B5>=0.75,"🔥 Almost!",IF(C5/B5>=0.5,"📈 Halfway","🚀 Building"))) -> 🚀 Building
A6: New Car Down Payment | B6: 8000 | C6: 1500 | D6: 300 | E6: =IFERROR((B6-C6)/D6,0) -> 21.666667 | F6: =IFERROR(C6/B6,0) -> 0.1875 | G6: =IFERROR(EDATE(TODAY(),INT(E6)),"Done") -> 46825 | H6: =IF(C6>=B6,"✅ Complete",IF(C6/B6>=0.75,"🔥 Almost!",IF(C6/B6>=0.5,"📈 Halfway","🚀 Building"))) -> 🚀 Building
A7: Home Down Payment | B7: 40000 | C7: 5000 | D7: 800 | E7: =IFERROR((B7-C7)/D7,0) -> 43.75 | F7: =IFERROR(C7/B7,0) -> 0.125 | G7: =IFERROR(EDATE(TODAY(),INT(E7)),"Done") -> 47496 | H7: =IF(C7>=B7,"✅ Complete",IF(C7/B7>=0.75,"🔥 Almost!",IF(C7/B7>=0.5,"📈 Halfway","🚀 Building"))) -> 🚀 Building
A8: Holiday / Gifts Fund | B8: 1500 | C8: 600 | D8: 150 | E8: =IFERROR((B8-C8)/D8,0) -> 6 | F8: =IFERROR(C8/B8,0) -> 0.4 | G8: =IFERROR(EDATE(TODAY(),INT(E8)),"Done") -> 46369 | H8: =IF(C8>=B8,"✅ Complete",IF(C8/B8>=0.75,"🔥 Almost!",IF(C8/B8>=0.5,"📈 Halfway","🚀 Building"))) -> 🚀 Building
A9: Electronics / Tech | B9: 1200 | C9: 300 | D9: 100 | E9: =IFERROR((B9-C9)/D9,0) -> 9 | F9: =IFERROR(C9/B9,0) -> 0.25 | G9: =IFERROR(EDATE(TODAY(),INT(E9)),"Done") -> 46459 | H9: =IF(C9>=B9,"✅ Complete",IF(C9/B9>=0.75,"🔥 Almost!",IF(C9/B9>=0.5,"📈 Halfway","🚀 Building"))) -> 🚀 Building
A10: Home Repairs Fund | B10: 5000 | C10: 2000 | D10: 200 | E10: =IFERROR((B10-C10)/D10,0) -> 15 | F10: =IFERROR(C10/B10,0) -> 0.4 | G10: =IFERROR(EDATE(TODAY(),INT(E10)),"Done") -> 46643 | H10: =IF(C10>=B10,"✅ Complete",IF(C10/B10>=0.75,"🔥 Almost!",IF(C10/B10>=0.5,"📈 Halfway","🚀 Building"))) -> 🚀 Building
A11: Investment Fund | B11: 10000 | C11: 3000 | D11: 500 | E11: =IFERROR((B11-C11)/D11,0) -> 14 | F11: =IFERROR(C11/B11,0) -> 0.3 | G11: =IFERROR(EDATE(TODAY(),INT(E11)),"Done") -> 46612 | H11: =IF(C11>=B11,"✅ Complete",IF(C11/B11>=0.75,"🔥 Almost!",IF(C11/B11>=0.5,"📈 Halfway","🚀 Building"))) -> 🚀 Building
A12: TOTAL | B12: =SUM(B4:B11) -> 83700 | C12: =SUM(C4:C11) -> 17400 | D12: =SUM(D4:D11) -> 2750

Sheet 📈 Net Worth
A1: 📈 NET WORTH TRACKER — Assets vs Liabilities
B3: TOTAL ASSETS | C3: TOTAL LIABILITIES | D3: NET WORTH
B4: =B15 -> 427000 | C4: =B25 -> 313000 | D4: =B27 -> 114000
A6: Assets
A7: Asset | B7: Value | C7: Type | D7: Notes
A8: Checking Account | B8: 5000 | C8: Cash
A9: Savings Account | B9: 12000 | C9: Cash
A10: Investment Portfolio | B10: 25000 | C10: Investment
A11: 401k / IRA | B11: 45000 | C11: Retirement
A12: Home Value | B12: 320000 | C12: Real Estate
A13: Car Value | B13: 18000 | C13: Vehicle
A14: Other Assets | B14: 2000 | C14: Other
A15: TOTAL ASSETS | B15: =SUM(B8:B14) -> 427000
A17: Liabilities
A18: Liability | B18: Balance | C18: APR % | D18: Notes
A19: Mortgage | B19: 285000 | C19: 0.07
A20: Car Loan | B20: 8500 | C20: 0.075
A21: Student Loan | B21: 12000 | C21: 0.068
A22: Credit Card A | B22: 3200 | C22: 0.2499
A23: Credit Card B | B23: 1800 | C23: 0.1999
A24: Personal Loan | B24: 2500 | C24: 0.15
A25: TOTAL LIABILITIES | B25: =SUM(B19:B24) -> 313000
A27: NET WORTH | B27: =B15-B25 -> 114000

Sheet ⚖ 50-30-20
A1: ⚖ 50 / 30 / 20 RULE — Budget Distribution
A3: Monthly Net Income | B3: ='⚙ Setup'!B7 -> 5000
A5: 50% — NEEDS
A6: Housing, Bills, Food, Transportation, Insurance
B7: Recommended | C7: Your Actual | D7: Difference
B8: =B3*0.5 -> 2500 | C8: =(SUM(Jan:Dec!C17)+SUM(Jan:Dec!C18)+SUM(Jan:Dec!C19)+SUM(Jan:Dec!C20)+SUM(Jan:Dec!C21)+SUM(Jan:Dec!C22))/12 -> 2980 | D8: =B8-C8 -> -480
A10: 30% — WANTS
A11: Entertainment, Dining Out, Shopping, Hobbies
B12: Recommended | C12: Your Actual | D12: Difference
B13: =B3*0.3 -> 1500 | C13: =(SUM(Jan:Dec!C23)+SUM(Jan:Dec!C24)+SUM(Jan:Dec!C25)+SUM(Jan:Dec!C27)+SUM(Jan:Dec!C28)+SUM(Jan:Dec!C30)+SUM(Jan:Dec!C31))/12 -> 684.58333 | D13: =B13-C13 -> 815.41667
A15: 20% — SAVINGS
A16: Emergency Fund, Investments, Debt Payoff
B17: Recommended | C17: Your Actual | D17: Difference
B18: =B3*0.2 -> 1000 | C18: ='📊 Annual Dashboard'!D20/12 -> 1447.9167 | D18: =B18-C18 -> -447.91667

Sheet 👫 Couples Budget
A1: 👫 COUPLES BUDGET — Shared & Individual Finances
B3: Partner 1 Name: | C3: Partner 1 | F3: Partner 2 Name: | G3: Partner 2
A5: Combined Income
A6: Source | B6: Partner 1 | C6: Partner 2 | D6: Combined | E6: % of Total
A7: Primary Salary | B7: 0 | C7: 0 | D7: =B7+C7 -> 0 | E7: =IFERROR(D7/D11,0) -> 0
A8: Secondary Income | B8: 0 | C8: 0 | D8: =B8+C8 -> 0 | E8: =IFERROR(D8/D11,0) -> 0
A9: Side Hustle | B9: 0 | C9: 0 | D9: =B9+C9 -> 0 | E9: =IFERROR(D9/D11,0) -> 0
A10: Other Income | B10: 0 | C10: 0 | D10: =B10+C10 -> 0 | E10: =IFERROR(D10/D11,0) -> 0
A11: TOTAL INCOME | B11: =SUM(B7:B10) -> 0 | C11: =SUM(C7:C10) -> 0 | D11: =SUM(D7:D10) -> 0 | E11: 100%
A13: Shared Expenses
A14: Category | B14: Total Cost | C14: Partner 1 Share % | D14: Partner 1 Pays | E14: Partner 2 Pays | F14: Notes
A15: Rent / Mortgage | B15: 1500 | C15: 0.5 | D15: =B15*C15 -> 750 | E15: =B15*(1-C15) -> 750
A16: Utilities | B16: 300 | C16: 0.5 | D16: =B16*C16 -> 150 | E16: =B16*(1-C16) -> 150
A17: Groceries | B17: 600 | C17: 0.5 | D17: =B17*C17 -> 300 | E17: =B17*(1-C17) -> 300
A18: Streaming Services | B18: 50 | C18: 0.5 | D18: =B18*C18 -> 25 | E18: =B18*(1-C18) -> 25
A19: Internet | B19: 80 | C19: 0.5 | D19: =B19*C19 -> 40 | E19: =B19*(1-C19) -> 40
A20: Eating Out | B20: 400 | C20: 0.5 | D20: =B20*C20 -> 200 | E20: =B20*(1-C20) -> 200
A21: Vacations | B21: 500 | C21: 0.5 | D21: =B21*C21 -> 250 | E21: =B21*(1-C21) -> 250
A22: Joint Savings | B22: 800 | C22: 0.5 | D22: =B22*C22 -> 400 | E22: =B22*(1-C22) -> 400
A23: TOTAL SHARED | B23: =SUM(B15:B22) -> 4230 | D23: =SUM(D15:D22) -> 2115 | E23: =SUM(E15:E22) -> 2115
A25: Individual Spending
A26: Category | B26: Partner 1 Budget | C26: Partner 1 Actual | D26: Partner 2 Budget | E26: Partner 2 Actual | F26: Notes
A27: Personal Shopping | B27: 0 | C27: 0 | D27: 0 | E27: 0
A28: Hobbies | B28: 0 | C28: 0 | D28: 0 | E28: 0
A29: Dining (personal) | B29: 0 | C29: 0 | D29: 0 | E29: 0
A30: Gym / Fitness | B30: 0 | C30: 0 | D30: 0 | E30: 0
A31: Personal Care | B31: 0 | C31: 0 | D31: 0 | E31: 0
A32: Subscriptions (personal) | B32: 0 | C32: 0 | D32: 0 | E32: 0

Sheet 🧠 ADHD View
A1: 🧠 ADHD-FRIENDLY BUDGET — Simple. Visual. Clear.
A2: Color-coded by category · Large text · No overwhelm
B4: 🏠 HOUSING
B5: =Jan!C17 -> 1500
B6: ← tap to update
B8: 🚗 TRANSPORT
B9: =Jan!C18 -> 350
B10: ← tap to update
B12: 🍎 FOOD
B13: =Jan!C19 -> 580
B14: ← tap to update
B16: ⚡ UTILITIES
B17: =Jan!C20 -> 180
B18: ← tap to update
B20: 🎉 FUN MONEY
B21: =Jan!C23 -> 120
B22: ← tap to update
B24: 💊 HEALTH
B25: =Jan!C22 -> 100
B26: ← tap to update
B28: 📚 EDUCATION
B29: =Jan!C26 -> 0
B30: ← tap to update
B32: 💰 SAVINGS
B33: =Jan!C18 -> 350
B34: ← tap to update

Sheet 📱 Subscriptions
A1: 📱 SUBSCRIPTION TRACKER — Stop Paying for Things You Forgot
A3: Service | B3: Monthly Cost | C3: Annual Cost | D3: Category | E3: Renewal Date | F3: Auto-renew? | G3: Keep/Cancel? | H3: Notes
A4: Netflix | B4: 17.99 | C4: =B4*12 -> 215.88 | D4: Streaming | F4: Yes | G4: ✓ Keep
A5: Spotify | B5: 11.99 | C5: =B5*12 -> 143.88 | D5: Music | F5: Yes | G5: ✓ Keep
A6: Amazon Prime | B6: 14.99 | C6: =B6*12 -> 179.88 | D6: Shopping | F6: Yes | G6: ✓ Keep
A7: YouTube Premium | B7: 13.99 | C7: =B7*12 -> 167.88 | D7: Video | F7: Yes | G7: ✓ Keep
A8: iCloud 200GB | B8: 2.99 | C8: =B8*12 -> 35.88 | D8: Storage | F8: Yes | G8: ✓ Keep
A9: Adobe CC | B9: 54.99 | C9: =B9*12 -> 659.88 | D9: Software | F9: Yes | G9: ✓ Keep
A10: ChatGPT Plus | B10: 20 | C10: =B10*12 -> 240 | D10: AI Tools | F10: Yes | G10: ✓ Keep
A11: Gym Membership | B11: 40 | C11: =B11*12 -> 480 | D11: Fitness | F11: Yes | G11: ✓ Keep
A12: Hulu | B12: 17.99 | C12: =B12*12 -> 215.88 | D12: Streaming | F12: Yes | G12: ✓ Keep
A13: Disney+ | B13: 13.99 | C13: =B13*12 -> 167.88 | D13: Streaming | F13: Yes | G13: ✓ Keep
A14: TOTAL / MONTH | B14: =SUM(B4:B13) -> 208.92 | C14: =SUM(C4:C13) -> 2507.04

Sheet 💵 Income Tracker
A1: 💵 INCOME TRACKER — All Income Sources
A3: Date | B3: Source / Description | C3: Amount | D3: Category | E3: Tax? | F3: After Tax | G3: Month | H3: Notes
A4: 01/15/2025 | B4: Primary Salary | C4: 4500 | D4: Wages | E4: Yes | F4: =IF(E4="Yes",C4*(1-0.25),C4) -> 3375 | G4: =IFERROR(TEXT(A4,"mmm"),"") -> 01/15/2025
A5: 01/29/2025 | B5: Primary Salary | C5: 4500 | D5: Wages | E5: Yes | F5: =IF(E5="Yes",C5*(1-0.25),C5) -> 3375 | G5: =IFERROR(TEXT(A5,"mmm"),"") -> 01/29/2025
A6: 01/10/2025 | B6: Freelance Project | C6: 800 | D6: Self-Employment | E6: Yes | F6: =IF(E6="Yes",C6*(1-0.25),C6) -> 600 | G6: =IFERROR(TEXT(A6,"mmm"),"") -> oct
A7: 02/15/2025 | B7: Primary Salary | C7: 4500 | D7: Wages | E7: Yes | F7: =IF(E7="Yes",C7*(1-0.25),C7) -> 3375 | G7: =IFERROR(TEXT(A7,"mmm"),"") -> 02/15/2025
A8: 02/28/2025 | B8: Primary Salary | C8: 4500 | D8: Wages | E8: Yes | F8: =IF(E8="Yes",C8*(1-0.25),C8) -> 3375 | G8: =IFERROR(TEXT(A8,"mmm"),"") -> 02/28/2025
A9: 02/20/2025 | B9: Rental Income | C9: 1200 | D9: Passive | E9: Yes | F9: =IF(E9="Yes",C9*(1-0.25),C9) -> 900 | G9: =IFERROR(TEXT(A9,"mmm"),"") -> 02/20/2025

Sheet 🎯 No-Spend Challenge
A1: 🎯 NO-SPEND CHALLENGE — 30-Day Money Detox
A3: Mark each day: ✅ No-Spend / 💸 Spent
A4: Day | B4: Date | C4: Status | D4: Amount Saved | E4: Notes
A5: 1 | D5: 0
A6: 2 | D6: 0
A7: 3 | D7: 0
A8: 4 | D8: 0
A9: 5 | D9: 0
A10: 6 | D10: 0
A11: 7 | D11: 0
A12: 8 | D12: 0
A13: 9 | D13: 0
A14: 10 | D14: 0
A15: 11 | D15: 0
A16: 12 | D16: 0
... A34: 30 | D34: 0
A36: ✅ No-Spend Days | D36: =COUNTIF(C5:C34,"✅") -> 0
A37: 💰 Total Saved | D37: =SUM(D5:D34) -> 0

Sheet 📖 Instructions
A1: 📖 HOW TO USE — Step by Step Guide
B3: STEP 1: Setup | C3: Go to '⚙ Setup' tab → Enter your name, monthly income, and savings goal %
B5: STEP 2: Monthly tracking | C5: Every month, open that month's tab (Jan, Feb...) → Enter income and actual expenses
B7: STEP 3: Bill Calendar | C7: Open '🗓 Bill Calendar' → Add all your recurring bills with due dates
B9: STEP 4: Debt Tracker | C9: Go to '💳 Debt Tracker' → Enter all debts, balances, and APRs
B11: STEP 5: Savings Goals | C11: Open '💰 Savings Tracker' → Set your savings goals and monthly contributions
B13: STEP 6: Net Worth | C13: Update '📈 Net Worth' monthly → Add current balances for all assets & liabilities
B15: STEP 7: 50/30/20 | C15: Check '⚖ 50-30-20' → Enter your monthly income to see the recommended split
B17: STEP 8: Dashboard | C17: Visit '📊 Annual Dashboard' to see your full year summary automatically
B19: STEP 9: Couples | C19: If budgeting with a partner → Use '👫 Couples Budget' tab
B21: STEP 10: ADHD Mode | C21: If you prefer visual budgeting → Use '🧠 ADHD View' for color-coded categories
